rapidunfurl/__init__.py
rapidunfurl/example.py
rapidunfurl/unfurl.py
rapidunfurl/provider_data/__init__.py
rapidunfurl/provider_data/custom.py
rapidunfurl/provider_data/noembed.py
rapidunfurl/provider_data/oembed.py
rapidunfurl-1.1.0.dist-info/LICENSE
rapidunfurl-1.1.0.dist-info/METADATA
rapidunfurl-1.1.0.dist-info/WHEEL
rapidunfurl-1.1.0.dist-info/top_level.txt
rapidunfurl-1.1.0.dist-info/RECORD
