Metadata-Version: 2.1
Name: rapidunfurl
Version: 1.1.0
Summary: Quickly extract metadata from URLs
Home-page: https://github.com/tdarwin/rapidunfurl
Author: Davin Taddeo
Author-email: davin@davintaddeo.com
License: License :: OSI Approved :: MIT License
Project-URL: Bug Tracker, https://github.com/tdarwin/rapidunfurl/issues
Classifier: Programming Language :: Python
Classifier: Programming Language :: Python :: 3
Classifier: Operating System :: OS Independent
Requires-Python: >=3.6
License-File: LICENSE
Requires-Dist: pyquery
Requires-Dist: requests
Requires-Dist: uritools
Requires-Dist: micawber
